HAbench/VideoTextConsistency.py
HAbench/__init__.py
HAbench/dynamicquality.py
HAbench/prompt_dict.py
HAbench/staticquality.py
HAbench/utils.py
HAbench/cli/__init__.py
HAbench/cli/evaluate.py
HAbench-0.1.0.dist-info/METADATA
HAbench-0.1.0.dist-info/WHEEL
HAbench-0.1.0.dist-info/entry_points.txt
HAbench-0.1.0.dist-info/top_level.txt
HAbench-0.1.0.dist-info/RECORD
