Metadata-Version: 2.1
Name: HAbench
Version: 0.1.0
Summary: Human Preference Aligned Video Generation Benchmark
License: Apache Software License 2.0
Project-URL: Source, https://github.com/HA-Video-Bench/HA-Video-Bench
Requires-Dist: numpy ==1.26.4
Requires-Dist: openai ==1.42.0
Requires-Dist: opencv ==4.6.0
Requires-Dist: opencv-python ==4.10.0
Requires-Dist: opencv-python-headless ==4.10.0
Requires-Dist: tqdm ==4.66.4
Requires-Dist: tenacity ==8.4.2
